pte_stats/__init__.py
pte_stats/cluster.py
pte_stats/permutation.py
pte_stats/timeseries.py
pte_stats-0.3.0.dist-info/METADATA
pte_stats-0.3.0.dist-info/WHEEL
pte_stats-0.3.0.dist-info/licenses/LICENSE
pte_stats-0.3.0.dist-info/RECORD
