Metadata-Version: 2.1
Name: pte-stats
Version: 0.3.0
Summary: An open-source software package for statistics with time series.
Project-URL: bugtracker, https://github.com/richardkoehler/pte-stats/issues
Project-URL: changelog, https://github.com/richardkoehler/pte-stats/blob/main/docs/CHANGELOG.md
Project-URL: repository, https://github.com/richardkoehler/pte-stats
Author: Richard M. Köhler
Maintainer: Richard M. Köhler
License: MIT License
License-File: LICENSE
Keywords: eeg,ieeg,statistics,timeseries
Classifier: Development Status :: 2 - Pre-Alpha
Classifier: License :: OSI Approved :: MIT License
Classifier: Programming Language :: Python
Classifier: Topic :: Software Development :: Libraries :: Python Modules
Requires-Python: >=3.10
Requires-Dist: joblib
Requires-Dist: numba
Requires-Dist: numpy
Requires-Dist: scikit-image
Requires-Dist: statsmodels
Provides-Extra: dev
Requires-Dist: black; extra == 'dev'
Requires-Dist: hatch; extra == 'dev'
Requires-Dist: mypy; extra == 'dev'
Requires-Dist: packaging; extra == 'dev'
Requires-Dist: pandas-stubs; extra == 'dev'
Requires-Dist: pre-commit; extra == 'dev'
Requires-Dist: pytest; extra == 'dev'
Requires-Dist: pytest-cov; extra == 'dev'
Requires-Dist: ruff; extra == 'dev'
Requires-Dist: tox; extra == 'dev'
